{
  "generated": "2026-05-21T23:38:36Z",
  "total_found": 10,
  "deals": [
    {
      "address": "9715 Tullamoor Dr, Saint Louis, MO, 63136",
      "price": 100000.0,
      "bedrooms": 4,
      "cashflow": 1119.28,
      "projected_cf": 606.7714618829668,
      "cap_rate": 14.15,
      "coc_pct": 36.4,
      "dscr": 2.76,
      "garry_score": 78.3,
      "fmr": 1812.0,
      "in_avenue_zip": true,
      "dscr_eligible": true,
      "hqs_score": 20.0,
      "crime_score": 50,
      "ai_summary": "This property presents a compelling investment opportunity characterized by exceptionally strong projected financial returns. The potential for high cash flow and a robust cap rate makes it attractive from a numbers perspective. The four-bedroom layout is well-suited for the Section 8 market, aligni",
      "ai_scores": {
        "property_quality": 20.0,
        "financial": 80.0,
        "hqs": 20.0,
        "location": 40.0,
        "s8_demand": 80.0
      },
      "zillow_url": "https://www.zillow.com/homes/9715-Tullamoor-Dr--Saint-Louis--MO--63136_rb/",
      "s8pro_url": "https://app.section8pro.com/deal-explorer/property/1151215",
      "scraped_at": "2026-05-21T09:08:55.685847"
    },
    {
      "address": "2502 Switzer Ave, Saint Louis, MO, 63136",
      "price": 100200.0,
      "bedrooms": 4,
      "cashflow": 1118.26,
      "projected_cf": 605.6274128067328,
      "cap_rate": 14.12,
      "coc_pct": 36.3,
      "dscr": 2.75,
      "garry_score": 72.5,
      "fmr": 1812.0,
      "in_avenue_zip": true,
      "dscr_eligible": true,
      "hqs_score": 40.0,
      "crime_score": 50,
      "ai_summary": "This property presents a significant investment risk primarily due to its location in an area with elevated crime rates and the absence of clear financial projections. The neighborhood's characteristics may pose challenges in attracting and retaining stable, long-term tenants, potentially impacting ",
      "ai_scores": {
        "property_quality": 20.0,
        "financial": 40.0,
        "hqs": 40.0,
        "location": 20.0,
        "s8_demand": 60.0
      },
      "zillow_url": "https://www.zillow.com/homes/2502-Switzer-Ave--Saint-Louis--MO--63136_rb/",
      "s8pro_url": "https://app.section8pro.com/deal-explorer/property/538168",
      "scraped_at": "2026-05-21T09:16:29.637784"
    },
    {
      "address": "10518 Renfrew Dr, Saint Louis, MO, 63137",
      "price": 104900.0,
      "bedrooms": 4,
      "cashflow": 1094.22,
      "projected_cf": 578.742259515232,
      "cap_rate": 13.48,
      "coc_pct": 33.1,
      "dscr": 2.63,
      "garry_score": 83.5,
      "fmr": 1812.0,
      "in_avenue_zip": true,
      "dscr_eligible": true,
      "hqs_score": 60.0,
      "crime_score": 50,
      "ai_summary": "This property presents a compelling financial profile with very strong projected cash flow and returns. The four-bedroom layout is highly desirable within the Section 8 market, and the projected rent is well-supported by local Fair Market Rent values, indicating a robust demand. The interior appears",
      "ai_scores": {
        "property_quality": 60.0,
        "financial": 80.0,
        "hqs": 60.0,
        "location": 40.0,
        "s8_demand": 80.0
      },
      "zillow_url": "https://www.zillow.com/homes/10518-Renfrew-Dr--Saint-Louis--MO--63137_rb/",
      "s8pro_url": "https://app.section8pro.com/deal-explorer/property/384620",
      "scraped_at": "2026-05-21T09:20:11.916577"
    },
    {
      "address": "8551 Oriole Ave, Saint Louis, MO, 63147",
      "price": 110000.0,
      "bedrooms": 4,
      "cashflow": 1068.13,
      "projected_cf": 549.5690080712634,
      "cap_rate": 12.86,
      "coc_pct": 30.0,
      "dscr": 2.51,
      "garry_score": 82.5,
      "fmr": 1812.0,
      "in_avenue_zip": true,
      "dscr_eligible": true,
      "hqs_score": 60.0,
      "crime_score": 50,
      "ai_summary": "This property presents a compelling investment opportunity based on its strong projected financial performance and market alignment. The financial metrics are exceptionally positive, indicating a high potential for immediate and sustained profitability. The property's size and bedroom count are well",
      "ai_scores": {
        "property_quality": 60.0,
        "financial": 80.0,
        "hqs": 60.0,
        "location": 40.0,
        "s8_demand": 80.0
      },
      "zillow_url": "https://www.zillow.com/homes/8551-Oriole-Ave--Saint-Louis--MO--63147_rb/",
      "s8pro_url": "https://app.section8pro.com/deal-explorer/property/1152161",
      "scraped_at": "2026-05-21T09:01:25.076060"
    },
    {
      "address": "4100 Ammann Ln, Saint Louis, MO, 63121",
      "price": 119900.0,
      "bedrooms": 4,
      "cashflow": 1017.49,
      "projected_cf": 492.9385787976771,
      "cap_rate": 11.8,
      "coc_pct": 24.7,
      "dscr": 2.3,
      "garry_score": 81.5,
      "fmr": 1812.0,
      "in_avenue_zip": true,
      "dscr_eligible": true,
      "hqs_score": 60.0,
      "crime_score": 50,
      "ai_summary": "This property presents a compelling investment opportunity, primarily driven by its strong projected cash flow and alignment with Section 8 market demand. The financial projections indicate a significant positive return, making it an attractive asset from a purely numerical standpoint. The property'",
      "ai_scores": {
        "property_quality": 60.0,
        "financial": 80.0,
        "hqs": 60.0,
        "location": 40.0,
        "s8_demand": 80.0
      },
      "zillow_url": "https://www.zillow.com/homes/4100-Ammann-Ln--Saint-Louis--MO--63121_rb/",
      "s8pro_url": "https://app.section8pro.com/deal-explorer/property/77339",
      "scraped_at": "2026-05-21T09:30:45.517349"
    },
    {
      "address": "8425 Halls Ferry Rd, Saint Louis, MO, 63147",
      "price": 120000.0,
      "bedrooms": 5,
      "cashflow": 1016.98,
      "projected_cf": 492.3665542595601,
      "cap_rate": 11.79,
      "coc_pct": 24.6,
      "dscr": 2.3,
      "garry_score": 81.1,
      "fmr": 1812.0,
      "in_avenue_zip": true,
      "dscr_eligible": true,
      "hqs_score": 80.0,
      "crime_score": 50,
      "ai_summary": "This property presents a compelling investment opportunity characterized by exceptionally strong projected cash flow and a high-yield financial profile. The recent luxury-level renovation, which includes all major systems, positions the asset for immediate rental income with minimal initial maintena",
      "ai_scores": {
        "property_quality": 20.0,
        "financial": 80.0,
        "hqs": 80.0,
        "location": 20.0,
        "s8_demand": 80.0
      },
      "zillow_url": "https://www.zillow.com/homes/8425-Halls-Ferry-Rd--Saint-Louis--MO--63147_rb/",
      "s8pro_url": "https://app.section8pro.com/deal-explorer/property/844031",
      "scraped_at": "2026-05-21T09:11:13.796846"
    },
    {
      "address": "106 Henquin Dr, Saint Louis, MO, 63135",
      "price": 100000.0,
      "bedrooms": 3,
      "cashflow": 982.48,
      "projected_cf": 487.75546188296676,
      "cap_rate": 12.72,
      "coc_pct": 29.3,
      "dscr": 2.52,
      "garry_score": 80.1,
      "fmr": 1660.0,
      "in_avenue_zip": true,
      "dscr_eligible": true,
      "hqs_score": 60.0,
      "crime_score": 50,
      "ai_summary": "This property presents a compelling financial profile on paper, with strong projected cash flow and returns. The potential to increase rent to meet the local Fair Market Rent further enhances its appeal. The home appears to be in reasonable condition, suggesting it could meet HQS standards with mini",
      "ai_scores": {
        "property_quality": 20.0,
        "financial": 80.0,
        "hqs": 60.0,
        "location": 20.0,
        "s8_demand": 80.0
      },
      "zillow_url": "https://www.zillow.com/homes/106-Henquin-Dr--Saint-Louis--MO--63135_rb/",
      "s8pro_url": "https://app.section8pro.com/deal-explorer/property/1151457",
      "scraped_at": "2026-05-21T09:08:31.776212"
    },
    {
      "address": "300 Rand Dr, Saint Louis, MO, 63135",
      "price": 104900.0,
      "bedrooms": 3,
      "cashflow": 957.42,
      "projected_cf": 459.72625951523196,
      "cap_rate": 12.12,
      "coc_pct": 26.3,
      "dscr": 2.41,
      "garry_score": 82.1,
      "fmr": 1660.0,
      "in_avenue_zip": true,
      "dscr_eligible": true,
      "hqs_score": 80.0,
      "crime_score": 50,
      "ai_summary": "This property presents a compelling investment opportunity based on its strong financial projections and physical condition. The projected cash flow and returns are robust, indicating significant profitability. The home's brick construction, hardwood floors, and updated features suggest it is well-m",
      "ai_scores": {
        "property_quality": 20.0,
        "financial": 80.0,
        "hqs": 80.0,
        "location": 20.0,
        "s8_demand": 80.0
      },
      "zillow_url": "https://www.zillow.com/homes/300-Rand-Dr--Saint-Louis--MO--63135_rb/",
      "s8pro_url": "https://app.section8pro.com/deal-explorer/property/1151799",
      "scraped_at": "2026-05-21T09:06:23.931540"
    }
  ]
}