{
  "generated": "2026-06-08T05:36:57.119267+10:00",
  "source": "health-engine v2",
  "device": "Apple Watch + Eight Sleep",
  "coaching": "Well recovered (84%) and 10.0h sleep. Full output available today \u2014 good day to push on priorities or train hard.",
  "today": {
    "date": "2026-06-08",
    "spoons": 11,
    "spoons_max": 12,
    "spoons_label": "Peak \u2014 push hard",
    "spoons_color": "green",
    "rings": {
      "sleep": {
        "value": 100,
        "unit": "%",
        "raw_hr": 10.0,
        "color": "blue",
        "label": "10.0h",
        "subtitle": "10.0h total \u00b7 deep 2.4h / REM 1.8h"
      },
      "recovery": {
        "value": 84,
        "unit": "%",
        "color": "green",
        "label": "GREEN \u2014 push hard",
        "subtitle": "HRV 56.1ms / RHR 65bpm"
      },
      "strain": {
        "value": 0,
        "unit": "/21",
        "color": "purple",
        "raw": {
          "value": 0,
          "max": 21,
          "kcal": 0,
          "steps": 0,
          "exercise_min": 0,
          "hr_load": 0.0
        },
        "subtitle": "0kcal / 0st / 0min ex"
      },
      "stress": {
        "value": 0,
        "unit": "%",
        "color": "gray",
        "label": "no data",
        "subtitle": "HR ?bpm vs RHR ?"
      }
    },
    "sleep_breakdown": {
      "total_hr": 10.0,
      "deep_hr": 2.41,
      "rem_hr": 1.76,
      "core_hr": 5.83,
      "awake_hr": 0,
      "in_bed_hr": 11.81,
      "source_override": "eight_sleep",
      "hrv_overnight": 56.1,
      "rhr_overnight": 65
    },
    "hrv_overnight": 56.1,
    "rhr_overnight": 65,
    "baseline_14d": {
      "hrv": 42.2,
      "rhr": 68.1,
      "sleep_hr": 7.1,
      "days_sampled": 0,
      "source": "Eight Sleep 7d + CSV 14d hybrid"
    },
    "baseline_30d": {
      "hrv": 23.8,
      "rhr": 80.0,
      "sleep_hr": 5.2,
      "days_sampled": 3,
      "source": "Apple Health CSV 30d avg"
    },
    "nutrition": {}
  },
  "history": []
}