{
  "updated": "2026-05-08T23:30:11.930694+10:00",
  "source": "dashboard-bridge",
  "data_age_hours": 0,
  "stale": false,
  "today": {
    "date": "2026-05-08",
    "sleep_total_hr": 3.841666666666667,
    "sleep_deep_hr": 1.8583333333333334,
    "sleep_rem_hr": 1.7166666666666668,
    "sleep_core_hr": null,
    "sleep_awake_hr": null,
    "sleep_in_bed_hr": null,
    "hrv_avg": 49.02,
    "resting_hr": 77.0,
    "resp_rate_avg": null,
    "steps": 4224,
    "active_energy_kcal": 655,
    "stand_hours": null
  },
  "yesterday": {
    "date": "2026-05-07",
    "sleep_total_hr": 4.283333333333334,
    "sleep_deep_hr": 1.25,
    "sleep_rem_hr": 0.4,
    "sleep_core_hr": null,
    "sleep_awake_hr": null,
    "sleep_in_bed_hr": null,
    "hrv_avg": 28.01,
    "resting_hr": 89.0,
    "resp_rate_avg": null,
    "steps": 8950,
    "active_energy_kcal": 847,
    "stand_hours": null
  },
  "spoons": {
    "score": 5,
    "label": "Restful \u2014 light movement, hydration, defer big decisions",
    "color": "orange",
    "sleep_norm": 0.0,
    "hrv_norm": 0.8505,
    "activity_norm": 0.528,
    "sleep_hr_used": 3.841666666666667,
    "hrv_used": 49.02,
    "steps_used": 4224,
    "computed_at": "2026-05-08T23:30:11.930713+10:00"
  },
  "last_pipeline_refresh": "2026-05-08T13:42:30.429781+00:00",
  "export_connected": false
}